obliquetree-1.0.5.dist-info/RECORD
obliquetree-1.0.5.dist-info/WHEEL
obliquetree-1.0.5.dist-info/top_level.txt
obliquetree-1.0.5.dist-info/METADATA
obliquetree-1.0.5.dist-info/licenses/LICENSE
obliquetree/__init__.py
obliquetree/utils.py
obliquetree/_pywrap.py
obliquetree/src/utils.cpp
obliquetree/src/base.cpython-310-darwin.so
obliquetree/src/oblique.cpp
obliquetree/src/ccp.cpython-310-darwin.so
obliquetree/src/__init__.py
obliquetree/src/base.cpp
obliquetree/src/tree.cpp
obliquetree/src/tree.cpython-310-darwin.so
obliquetree/src/metric.cpp
obliquetree/src/metric.cpython-310-darwin.so
obliquetree/src/ccp.cpp
obliquetree/src/oblique.cpython-310-darwin.so
obliquetree/src/utils.cpython-310-darwin.so
