Metadata-Version: 2.4
Name: obliquetree
Version: 1.0.5
Summary: Traditional and Oblique Decision Tree
Author-email: Samet Copur <sametcopur@yahoo.com>
License-Expression: MIT
Project-URL: Documentation, https://obliquetree.readthedocs.io/en/latest/
Project-URL: Repository, https://github.com/sametcopur/obliquetree
Project-URL: Tracker, https://github.com/sametcopur/obliquetree/issues
Keywords: python,data-science,machine-learning,machine-learning-library,explainable-ai,decision-tree,oblique-tree
Classifier: Programming Language :: Python :: 3
Classifier: Operating System :: OS Independent
Requires-Python: >=3.10
License-File: LICENSE
Requires-Dist: numpy>=2.2.1
Requires-Dist: scipy>=1.15.0
Dynamic: license-file
